demo_02/__init__.py
demo_02/main.py
demo_02-0.1.0.dist-info/METADATA
demo_02-0.1.0.dist-info/entry_points.txt
demo_02-0.1.0.dist-info/WHEEL
demo_02-0.1.0.dist-info/RECORD
