Metadata-Version: 2.1
Name: demo-02
Version: 0.1.0
Summary: 
Author: Rizki Nur Barokah
Author-email: rizki@jkt1.ebdesk.com
Requires-Python: >=3.10,<4.0
Classifier: Programming Language :: Python :: 3
Classifier: Programming Language :: Python :: 3.10
Classifier: Programming Language :: Python :: 3.11
Requires-Dist: typer (>=0.7.0,<0.8.0)
